katie/__init__.py
katie/cli.py
katie-0.2.0.dist-info/LICENSE
katie-0.2.0.dist-info/METADATA
katie-0.2.0.dist-info/WHEEL
katie-0.2.0.dist-info/entry_points.txt
katie-0.2.0.dist-info/top_level.txt
katie-0.2.0.dist-info/RECORD
