Metadata-Version: 2.1
Name: katie
Version: 0.2.0
Summary: Kubernetes utilities
Home-page: UNKNOWN
License: UNKNOWN
Platform: UNKNOWN
Requires-Dist: click
